src/checkmd5.py
md5checker-0.2.1.dist-info/DESCRIPTION.rst
md5checker-0.2.1.dist-info/top_level.txt
md5checker-0.2.1.dist-info/entry_points.txt
md5checker-0.2.1.dist-info/metadata.json
md5checker-0.2.1.dist-info/WHEEL
md5checker-0.2.1.dist-info/METADATA
md5checker-0.2.1.dist-info/pbr.json
md5checker-0.2.1.dist-info/RECORD
md5checker/checkmd5.py
md5checker/__init__.py
