Metadata-Version: 2.0
Name: md5checker
Version: 0.2.1
Summary: Check md5 hash of file.
Home-page: https://github.com/trendsetter37/md5-checker
Author: Javis Sullivan
Author-email: javissullivan@gmail.com
License: MIT
Keywords: md5 hash security
Platform: UNKNOWN
Classifier: Development Status :: 3 - Alpha
Classifier: Intended Audience :: Developers
Classifier: Topic :: Security
Classifier: Topic :: Security :: Cryptography
Classifier: Intended Audience :: End Users/Desktop
Classifier: License :: OSI Approved :: MIT License
Classifier: Programming Language :: Python :: 2.6
Classifier: Programming Language :: Python :: 2.7
Classifier: Programming Language :: Python :: 3
Classifier: Programming Language :: Python :: 3.3
Classifier: Programming Language :: Python :: 3.4
Classifier: Programming Language :: Python :: 3.5
